MANIFEST.in
README.rst
requirements.txt
setup.py
django_tasker_geobase/__init__.py
django_tasker_geobase/admin.py
django_tasker_geobase/apps.py
django_tasker_geobase/converters.py
django_tasker_geobase/geocoder.py
django_tasker_geobase/models.py
django_tasker_geobase/serializer.py
django_tasker_geobase/urls.py
django_tasker_geobase/views.py
django_tasker_geobase.egg-info/PKG-INFO
django_tasker_geobase.egg-info/SOURCES.txt
django_tasker_geobase.egg-info/dependency_links.txt
django_tasker_geobase.egg-info/requires.txt
django_tasker_geobase.egg-info/top_level.txt
django_tasker_geobase/management/__init__.py
django_tasker_geobase/management/commands/__init__.py
django_tasker_geobase/management/commands/openweathermap.py
django_tasker_geobase/migrations/0001_initial.py
django_tasker_geobase/migrations/0002_geobase_openweathermap.py
django_tasker_geobase/migrations/0003_weather.py
django_tasker_geobase/migrations/__init__.py
tests/__init__.py
tests/settings.py
tests/test_geo.py
tests/urls.py
tests/wsgi.py